dash_cad_to_graph/__init__.py
dash_cad_to_graph/processor.py
dash_cad_to_graph/examples/__init__.py
dash_cad_to_graph/examples/app.py
dash_cad_to_graph-0.3.dist-info/LICENSE
dash_cad_to_graph-0.3.dist-info/METADATA
dash_cad_to_graph-0.3.dist-info/WHEEL
dash_cad_to_graph-0.3.dist-info/top_level.txt
dash_cad_to_graph-0.3.dist-info/RECORD
